examples/__init__.py
examples/data/k_line/K_1M/FUT.GC/2021-03-15.csv
examples/data/k_line/K_1M/FUT.GC/2021-03-16.csv
examples/data/k_line/K_1M/FUT.GC/2021-03-17.csv
examples/data/k_line/K_1M/FUT.SI/2021-03-15.csv
examples/data/k_line/K_1M/FUT.SI/2021-03-16.csv
examples/data/k_line/K_1M/FUT.SI/2021-03-17.csv
examples/data/k_line/K_1M/HK.01157/2021-03-15.csv
examples/data/k_line/K_1M/HK.01157/2021-03-16.csv
examples/data/k_line/K_1M/HK.01157/2021-03-17.csv
examples/demo_strategy/__init__.py
examples/demo_strategy/demo_strategy.py
examples/demo_strategy/main_demo.py
qtrader/__init__.py
qtrader/config/__init__.py
qtrader/config/config.py
qtrader/config/config_sample.py
qtrader/core/__init__.py
qtrader/core/balance.py
qtrader/core/constants.py
qtrader/core/data.py
qtrader/core/deal.py
qtrader/core/engine.cp38-win_amd64.pyd
qtrader/core/engine.cpython-38-darwin.so
qtrader/core/engine.cpython-38-x86_64-linux-gnu.so
qtrader/core/engine.py
qtrader/core/event_engine.cp38-win_amd64.pyd
qtrader/core/event_engine.cpython-38-darwin.so
qtrader/core/event_engine.cpython-38-x86_64-linux-gnu.so
qtrader/core/event_engine.py
qtrader/core/logger.py
qtrader/core/order.py
qtrader/core/portfolio.py
qtrader/core/position.py
qtrader/core/security.py
qtrader/core/setup.py
qtrader/core/strategy.py
qtrader/core/utility.py
qtrader/gateways/__init__.py
qtrader/gateways/base_gateway.py
qtrader/gateways/instrument_cfg.yaml
qtrader/gateways/backtest/__init__.py
qtrader/gateways/backtest/backtest_gateway.py
qtrader/gateways/cqg/__init__.py
qtrader/gateways/cqg/cqg_fees.py
qtrader/gateways/cqg/cqg_gateway.py
qtrader/gateways/cqg/wrapper/CELEnvironment.py
qtrader/gateways/cqg/wrapper/__init__.py
qtrader/gateways/cqg/wrapper/cqg_api.py
qtrader/gateways/futu/__init__.py
qtrader/gateways/futu/futu_fees.py
qtrader/gateways/futu/futu_gateway.py
qtrader/gateways/ib/__init__.py
qtrader/gateways/ib/ib_fees.py
qtrader/gateways/ib/ib_gateway.py
qtrader/plugins/__init__.py
qtrader/plugins/analysis/__init__.py
qtrader-0.0.4.dist-info/METADATA
qtrader-0.0.4.dist-info/WHEEL
qtrader-0.0.4.dist-info/entry_points.txt
qtrader-0.0.4.dist-info/top_level.txt
qtrader-0.0.4.dist-info/RECORD
