Metadata-Version: 2.1
Name: qtrader
Version: 0.0.4
Summary: Qtrader: Event-Driven Algorithmic Trading Engine
Home-page: UNKNOWN
Author: josephchen
Author-email: josephchenhk@gmail.com
License: JXW
Keywords: Quantitative Trading,Qtrader,Backtest
Platform: any
Requires-Dist: sqlalchemy
Requires-Dist: pandas
Requires-Dist: numpy
Requires-Dist: pytz
Requires-Dist: clickhouse-driver
Requires-Dist: matplotlib
Requires-Dist: plotly
Requires-Dist: python-telegram-bot
Requires-Dist: dash
